colorfultable/__init__.py
colorfultable/colors.py
colorfultable/ctcore.py
colorfultable/demo.py
colorfultable/test.py
colorfultable-201003.0.52.dist-info/LICENSE
colorfultable-201003.0.52.dist-info/METADATA
colorfultable-201003.0.52.dist-info/WHEEL
colorfultable-201003.0.52.dist-info/top_level.txt
colorfultable-201003.0.52.dist-info/RECORD
