Metadata-Version: 2.1
Name: colorfultable
Version: 201003.0.52
Summary: A module to help print beautiful table on the terminal.
Home-page: https://gitee.com/hrpzcf/colorfultable
Author: hrpzcf
Author-email: hrpzcf@foxmail.com
Maintainer: hrpzcf
Maintainer-email: hrpzcf@foxmail.com
License: MIT License
Keywords: table,console,terminal,colorful,text
Platform: any
Classifier: Development Status :: 3 - Alpha
Classifier: Environment :: Console
Classifier: License :: OSI Approved :: MIT License
Classifier: Programming Language :: Python :: 3
Requires-Python: >=3.5
Requires-Dist: colorama (>=0.4.3)
